{"nodes": [{"id": "src_components_deep_research_researchtemplates_tsx", "label": "ResearchTemplates.tsx", "file_type": "code", "source_file": "src\\components\\deep-research\\ResearchTemplates.tsx", "source_location": "L1"}, {"id": "researchtemplates_researchtemplates", "label": "ResearchTemplates()", "file_type": "code", "source_file": "src\\components\\deep-research\\ResearchTemplates.tsx", "source_location": "L12"}], "edges": [{"source": "src_components_deep_research_researchtemplates_tsx", "target": "deep_research_config", "relation": "imports_from", "confidence": "EXTRACTED", "source_file": "src\\components\\deep-research\\ResearchTemplates.tsx", "source_location": "L3", "weight": 1.0}, {"source": "src_components_deep_research_researchtemplates_tsx", "target": "researchtemplates_researchtemplates", "relation": "contains", "confidence": "EXTRACTED", "source_file": "src\\components\\deep-research\\ResearchTemplates.tsx", "source_location": "L12", "weight": 1.0}]}