{"nodes": [{"id": "src_lib_api_research_threads_ts", "label": "threads.ts", "file_type": "code", "source_file": "src\\lib\\api\\research\\threads.ts", "source_location": "L1"}, {"id": "threads_listresearchthreads", "label": "listResearchThreads()", "file_type": "code", "source_file": "src\\lib\\api\\research\\threads.ts", "source_location": "L26"}, {"id": "threads_createresearchthread", "label": "createResearchThread()", "file_type": "code", "source_file": "src\\lib\\api\\research\\threads.ts", "source_location": "L37"}, {"id": "threads_deleteresearchthread", "label": "deleteResearchThread()", "file_type": "code", "source_file": "src\\lib\\api\\research\\threads.ts", "source_location": "L60"}], "edges": [{"source": "src_lib_api_research_threads_ts", "target": "src_lib_api_research_core_client", "relation": "imports_from", "confidence": "EXTRACTED", "source_file": "src\\lib\\api\\research\\threads.ts", "source_location": "L5", "weight": 1.0}, {"source": "src_lib_api_research_threads_ts", "target": "src_lib_api_research_config", "relation": "imports_from", "confidence": "EXTRACTED", "source_file": "src\\lib\\api\\research\\threads.ts", "source_location": "L6", "weight": 1.0}, {"source": "src_lib_api_research_threads_ts", "target": "threads_listresearchthreads", "relation": "contains", "confidence": "EXTRACTED", "source_file": "src\\lib\\api\\research\\threads.ts", "source_location": "L26", "weight": 1.0}, {"source": "src_lib_api_research_threads_ts", "target": "threads_createresearchthread", "relation": "contains", "confidence": "EXTRACTED", "source_file": "src\\lib\\api\\research\\threads.ts", "source_location": "L37", "weight": 1.0}, {"source": "src_lib_api_research_threads_ts", "target": "threads_deleteresearchthread", "relation": "contains", "confidence": "EXTRACTED", "source_file": "src\\lib\\api\\research\\threads.ts", "source_location": "L60", "weight": 1.0}]}