{"nodes": [{"id": "src_lib_analyse_errors_ts", "label": "errors.ts", "file_type": "code", "source_file": "src\\lib\\analyse\\errors.ts", "source_location": "L1"}, {"id": "errors_analysiscancellederror", "label": "AnalysisCancelledError", "file_type": "code", "source_file": "src\\lib\\analyse\\errors.ts", "source_location": "L1"}, {"id": "errors_analysiscancellederror_constructor", "label": ".constructor()", "file_type": "code", "source_file": "src\\lib\\analyse\\errors.ts", "source_location": "L2"}], "edges": [{"source": "src_lib_analyse_errors_ts", "target": "errors_analysiscancellederror", "relation": "contains", "confidence": "EXTRACTED", "source_file": "src\\lib\\analyse\\errors.ts", "source_location": "L1", "weight": 1.0}, {"source": "errors_analysiscancellederror", "target": "errors_analysiscancellederror_constructor", "relation": "method", "confidence": "EXTRACTED", "source_file": "src\\lib\\analyse\\errors.ts", "source_location": "L2", "weight": 1.0}]}