{"nodes": [{"id": "src_components_deep_research_workspacethinkingstate_tsx", "label": "WorkspaceThinkingState.tsx", "file_type": "code", "source_file": "src\\components\\deep-research\\WorkspaceThinkingState.tsx", "source_location": "L1"}], "edges": [{"source": "src_components_deep_research_workspacethinkingstate_tsx", "target": "react", "relation": "imports_from", "confidence": "EXTRACTED", "source_file": "src\\components\\deep-research\\WorkspaceThinkingState.tsx", "source_location": "L3", "weight": 1.0}, {"source": "src_components_deep_research_workspacethinkingstate_tsx", "target": "usedeepresearch", "relation": "imports_from", "confidence": "EXTRACTED", "source_file": "src\\components\\deep-research\\WorkspaceThinkingState.tsx", "source_location": "L4", "weight": 1.0}, {"source": "src_components_deep_research_workspacethinkingstate_tsx", "target": "activity_log_simulator", "relation": "imports_from", "confidence": "EXTRACTED", "source_file": "src\\components\\deep-research\\WorkspaceThinkingState.tsx", "source_location": "L5", "weight": 1.0}]}